scsciipy
