Metadata-Version: 2.1
Name: scsciipy
Version: 0.1
Summary: scsciipy
Author-email: ilapronin0700@gmail.com
